tieto/__init__.py
tieto/async_database.py
tieto/database.py
tieto/typing.py
tieto-0.2.2.dist-info/WHEEL
tieto-0.2.2.dist-info/METADATA
tieto-0.2.2.dist-info/RECORD
